{
  "type": "excalidraw",
  "version": 2,
  "source": "https://marketplace.visualstudio.com/items?itemName=pomdtr.excalidraw-editor",
  "elements": [
    {
      "id": "MeyNCCdXtHtyRuTKDoaZ5",
      "type": "ellipse",
      "x": -20,
      "y": 1000,
      "width": 440,
      "height": 440,
      "angle": 0,
      "strokeColor": "#343a40",
      "backgroundColor": "#495057",
      "fillStyle": "solid",
      "strokeWidth": 1,
      "strokeStyle": "solid",
      "roughness": 0,
      "opacity": 100,
      "groupIds": [],
      "strokeSharpness": "sharp",
      "seed": 1940988684,
      "version": 41,
      "versionNonce": 1389339916,
      "isDeleted": false,
      "boundElements": null,
      "updated": 1668055653210,
      "link": null,
      "locked": false
    },
    {
      "id": "y1MF7AUOpiCG9rDOorjcL",
      "type": "ellipse",
      "x": 680,
      "y": 860,
      "width": 420,
      "height": 400,
      "angle": 0,
      "strokeColor": "#343a40",
      "backgroundColor": "#495057",
      "fillStyle": "solid",
      "strokeWidth": 1,
      "strokeStyle": "solid",
      "roughness": 0,
      "opacity": 100,
      "groupIds": [],
      "strokeSharpness": "sharp",
      "seed": 1553013132,
      "version": 31,
      "versionNonce": 135971596,
      "isDeleted": false,
      "boundElements": null,
      "updated": 1668055676465,
      "link": null,
      "locked": false
    },
    {
      "id": "JZ9j3sOQuip7xcQ333fLI",
      "type": "ellipse",
      "x": 640,
      "y": 1300,
      "width": 140,
      "height": 120,
      "angle": 0,
      "strokeColor": "#343a40",
      "backgroundColor": "#495057",
      "fillStyle": "solid",
      "strokeWidth": 1,
      "strokeStyle": "solid",
      "roughness": 0,
      "opacity": 100,
      "groupIds": [],
      "strokeSharpness": "sharp",
      "seed": 2132308660,
      "version": 12,
      "versionNonce": 783100684,
      "isDeleted": false,
      "boundElements": null,
      "updated": 1668055682630,
      "link": null,
      "locked": false
    },
    {
      "id": "5FVUKULmOVxFOt__OIqnq",
      "type": "text",
      "x": 1109.1359756711927,
      "y": 1330.7139400906033,
      "width": 72,
      "height": 27,
      "angle": 0,
      "strokeColor": "#343a40",
      "backgroundColor": "#495057",
      "fillStyle": "solid",
      "strokeWidth": 1,
      "strokeStyle": "solid",
      "roughness": 0,
      "opacity": 100,
      "groupIds": [],
      "strokeSharpness": "sharp",
      "seed": 1045945268,
      "version": 9,
      "versionNonce": 1740792244,
      "isDeleted": false,
      "boundElements": null,
      "updated": 1668055692031,
      "link": null,
      "locked": false,
      "text": "Bubbles",
      "fontSize": 20,
      "fontFamily": 1,
      "textAlign": "left",
      "verticalAlign": "top",
      "baseline": 22,
      "containerId": null,
      "originalText": "Bubbles"
    },
    {
      "id": "9YAt5pMqyceI4a997Cv8N",
      "type": "text",
      "x": 400,
      "y": 960,
      "width": 175.60817972818992,
      "height": 58.53605990939664,
      "angle": 0,
      "strokeColor": "#c92a2a",
      "backgroundColor": "#495057",
      "fillStyle": "solid",
      "strokeWidth": 1,
      "strokeStyle": "solid",
      "roughness": 0,
      "opacity": 100,
      "groupIds": [],
      "strokeSharpness": "sharp",
      "seed": 571134260,
      "version": 34,
      "versionNonce": 1632165772,
      "isDeleted": false,
      "boundElements": null,
      "updated": 1668055729051,
      "link": null,
      "locked": false,
      "text": "Bubbles",
      "fontSize": 46.82884792751732,
      "fontFamily": 1,
      "textAlign": "left",
      "verticalAlign": "top",
      "baseline": 41.53605990939664,
      "containerId": null,
      "originalText": "Bubbles"
    }
  ],
  "appState": {
    "gridSize": 20,
    "viewBackgroundColor": "#333"
  },
  "files": {}
}